{
  "last_updated": "2026-03-30T20:08:08.951553+02:00",
  "articles": [
    {
      "id": "brk-20260330-cca7b9",
      "type": "breaking",
      "category": "usa",
      "badge": "USA",
      "headline": "ICE announces death of another Mexican detainee in US immigration custody",
      "excerpt": "Mexico's President Claudia Sheinbaum says her country will take steps to protest death of another Mexican citizen in US.",
      "source": "Al Jazeera",
      "date": "30 Mar 2026",
      "timestamp": "2026-03-30T17:20:51Z",
      "url": "https://www.aljazeera.com/news/2026/3/30/ice-announces-death-of-another-mexican-detainee-in-us-immigration-custody?traffic_source=rss",
      "image": ""
    },
    {
      "id": "brk-20260330-8364df",
      "type": "breaking",
      "category": "europe",
      "badge": "Spain",
      "headline": "Spain closes airspace to US aircraft involved in Iran war",
      "excerpt": "It follows a decision by the Spanish government to deny the US use of the two jointly run military bases in Andalusia.",
      "source": "BBC News",
      "date": "30 Mar 2026",
      "timestamp": "2026-03-30T15:29:15Z",
      "url": "https://www.bbc.com/news/articles/cwy368j1e3lo?at_medium=RSS&at_campaign=rss",
      "image": "https://ichef.bbci.co.uk/ace/standard/240/cpsprodpb/a516/live/5f6b8700-2c34-11f1-b8c9-f5058c0aec9a.jpg"
    },
    {
      "id": "brk-20260330-be4122",
      "type": "breaking",
      "category": "europe",
      "badge": "UK",
      "headline": "Zelensky says allies asked him to scale back attacks on Russian energy",
      "excerpt": "Ukraine's president says partners asked if the attacks could be \"reduced\" as prices soar due to the Iran war.",
      "source": "BBC News",
      "date": "30 Mar 2026",
      "timestamp": "2026-03-30T17:53:51Z",
      "url": "https://www.bbc.com/news/articles/c0e7lrxrelwo?at_medium=RSS&at_campaign=rss",
      "image": "https://ichef.bbci.co.uk/ace/standard/240/cpsprodpb/f026/live/0d729d50-2c5a-11f1-862e-73ba828c2693.jpg"
    },
    {
      "id": "brk-20260330-cafb2e",
      "type": "breaking",
      "category": "usa",
      "badge": "Security",
      "headline": "Kris Jenner's image spreads in Chinese social media good luck trend",
      "excerpt": "Hundreds of thousands of posts have been shared in the past three days as users hope for prosperity",
      "source": "BBC News",
      "date": "30 Mar 2026",
      "timestamp": "2026-03-30T12:59:23Z",
      "url": "https://www.bbc.com/news/articles/c0rx57zgz52o?at_medium=RSS&at_campaign=rss",
      "image": "https://ichef.bbci.co.uk/ace/standard/240/cpsprodpb/86a5/live/faaf16e0-2c3a-11f1-9d83-af3423d2a1a1.jpg"
    },
    {
      "id": "icymi-20260330-ec0aea",
      "type": "icymi",
      "category": "africa",
      "badge": "Nigeria",
      "headline": "48-hour curfew imposed after attack on bar in Nigerian city",
      "excerpt": "The raid led to revenge attacks in Jos, with 22 reported dead so far in one of the most volatile parts of the country.",
      "source": "BBC Africa",
      "date": "30 Mar 2026",
      "timestamp": "2026-03-30T16:44:28Z",
      "url": "https://www.bbc.com/news/articles/cvg4q9n573do?at_medium=RSS&at_campaign=rss",
      "image": "https://ichef.bbci.co.uk/ace/standard/240/cpsprodpb/93fb/live/3c5c3dd0-2c2b-11f1-8768-1105331460e6.jpg"
    },
    {
      "id": "icymi-20260330-d075a9",
      "type": "icymi",
      "category": "africa",
      "badge": "Africa",
      "headline": "Caf general secretary steps down amid Afcon final fallout",
      "excerpt": "Veron Mosengo-Omba, a controversial figure, leaves at a turbulent time for African football.",
      "source": "BBC Africa",
      "date": "29 Mar 2026",
      "timestamp": "2026-03-29T13:53:17Z",
      "url": "https://www.bbc.com/news/articles/cx2w8d1q70vo?at_medium=RSS&at_campaign=rss",
      "image": "https://ichef.bbci.co.uk/ace/standard/240/cpsprodpb/65b2/live/8fe83090-2b76-11f1-915e-076b1d4be1dd.jpg"
    },
    {
      "id": "icymi-20260330-8a0eaf",
      "type": "icymi",
      "category": "europe",
      "badge": "EU",
      "headline": "Thieves steal Renoir, C\u00e9zanne and Matisse paintings in three-minute\u2026",
      "excerpt": "The paintings were taken from a museum in Parma by four masked men in the middle of the night, police say.",
      "source": "BBC Europe",
      "date": "29 Mar 2026",
      "timestamp": "2026-03-29T21:29:56Z",
      "url": "https://www.bbc.com/news/articles/cn4vw2xmpzzo?at_medium=RSS&at_campaign=rss",
      "image": "https://ichef.bbci.co.uk/ace/standard/240/cpsprodpb/063a/live/02dc33f0-2c1f-11f1-b297-95b0a0a8331e.jpg"
    },
    {
      "id": "icymi-20260330-e6518c",
      "type": "icymi",
      "category": "europe",
      "badge": "Italy",
      "headline": "Italy investigates Sephora and Benefit over marketing skincare to children",
      "excerpt": "The Italian Competition Authority said luxury goods giant LVMH appears to have adopted \"particularly insidious\" marketing strategies.",
      "source": "BBC Europe",
      "date": "29 Mar 2026",
      "timestamp": "2026-03-29T19:37:03Z",
      "url": "https://www.bbc.com/news/articles/c3dlk93m7jyo?at_medium=RSS&at_campaign=rss",
      "image": "https://ichef.bbci.co.uk/ace/standard/240/cpsprodpb/3667/live/fe0e0750-2ba0-11f1-a79a-77e93010d956.png"
    },
    {
      "id": "icymi-20260330-f57baf",
      "type": "icymi",
      "category": "europe",
      "badge": "France",
      "headline": "Three arrested in Paris after attempted bomb attack outside Bank of America",
      "excerpt": "France's anti-terrorism prosecutor's office said it had immediately taken over the investigation.",
      "source": "BBC Europe",
      "date": "29 Mar 2026",
      "timestamp": "2026-03-29T15:33:36Z",
      "url": "https://www.bbc.com/news/articles/cd9v234j2v7o?at_medium=RSS&at_campaign=rss",
      "image": "https://ichef.bbci.co.uk/ace/standard/240/cpsprodpb/ec5b/live/84304ed0-2b81-11f1-9b12-e7dc1d4ddef6.jpg"
    },
    {
      "id": "icymi-20260330-2a7fc3",
      "type": "icymi",
      "category": "usa",
      "badge": "USA",
      "headline": "First stop, the Moon. Next stop, Mars? Why Nasa's mission matters",
      "excerpt": "From a race with China to lunar discoveries, the US is investing time, effort and money to head to the Moon - and beyond.",
      "source": "BBC News",
      "date": "29 Mar 2026",
      "timestamp": "2026-03-29T23:50:21Z",
      "url": "https://www.bbc.com/news/articles/cd6wp6xenv0o?at_medium=RSS&at_campaign=rss",
      "image": "https://ichef.bbci.co.uk/ace/standard/240/cpsprodpb/d91a/live/1ce46b10-29e4-11f1-a79a-77e93010d956.jpg"
    },
    {
      "id": "icymi-20260330-5bafca",
      "type": "icymi",
      "category": "usa",
      "badge": "USA",
      "headline": "Partial government shutdown becomes the longest in US history",
      "excerpt": "The 44-day funding lapse for the Department of Homeland Security has led to travel chaos at US airports.",
      "source": "BBC News",
      "date": "30 Mar 2026",
      "timestamp": "2026-03-30T01:13:51Z",
      "url": "https://www.bbc.com/news/articles/cyv1qpzq5v7o?at_medium=RSS&at_campaign=rss",
      "image": "https://ichef.bbci.co.uk/ace/standard/240/cpsprodpb/9a60/live/cdacf7f0-2ba1-11f1-b878-d327a1a30108.jpg"
    },
    {
      "id": "icymi-20260330-a9fde1",
      "type": "icymi",
      "category": "finance",
      "badge": "Oil",
      "headline": "What was the 1970s oil crisis, and are we heading for something worse?",
      "excerpt": "While both crises involve oil, experts say there are some important differences between what happened in the 1970s and today.",
      "source": "BBC Business",
      "date": "30 Mar 2026",
      "timestamp": "2026-03-30T15:22:18Z",
      "url": "https://www.bbc.com/news/articles/c78lj4976lvo?at_medium=RSS&at_campaign=rss",
      "image": "https://ichef.bbci.co.uk/ace/standard/240/cpsprodpb/e9e7/live/befaf650-2c2b-11f1-b8c9-f5058c0aec9a.jpg"
    },
    {
      "id": "icymi-20260330-9015a5",
      "type": "icymi",
      "category": "finance",
      "badge": "Oil",
      "headline": "Oil rises and Asia shares slide as Iran war enters fifth week",
      "excerpt": "It comes after Iran-backed Houthi rebels in Yemen joined the conflict by striking Israel over the weekend.",
      "source": "BBC Business",
      "date": "30 Mar 2026",
      "timestamp": "2026-03-30T15:35:40Z",
      "url": "https://www.bbc.com/news/articles/cz905eyjznno?at_medium=RSS&at_campaign=rss",
      "image": "https://ichef.bbci.co.uk/ace/standard/240/cpsprodpb/a744/live/29a533f0-2bdf-11f1-b2aa-4d44460d139f.jpg"
    },
    {
      "id": "icymi-20260330-227d64",
      "type": "icymi",
      "category": "finance",
      "badge": "Oil",
      "headline": "How Trump and the oil markets move in sync: A tango in five charts",
      "excerpt": "Oil markets have been sensitive to Donald Trump's comments on the war. But are traders growing less responsive?",
      "source": "BBC Business",
      "date": "30 Mar 2026",
      "timestamp": "2026-03-30T14:10:06Z",
      "url": "https://www.bbc.com/news/articles/cvgk8zk9epgo?at_medium=RSS&at_campaign=rss",
      "image": "https://ichef.bbci.co.uk/ace/standard/240/cpsprodpb/afff/live/0ed104c0-29fd-11f1-99ef-b5dfea7d5974.jpg"
    },
    {
      "id": "icymi-20260330-7a4040",
      "type": "icymi",
      "category": "finance",
      "badge": "Finance",
      "headline": "Cut taxes on energy bills before giving bailouts, Badenoch says",
      "excerpt": "The Tory leader refuses to rule out direct payments to households if bills spike but says this would come at a cost.",
      "source": "BBC Business",
      "date": "29 Mar 2026",
      "timestamp": "2026-03-29T11:12:33Z",
      "url": "https://www.bbc.com/news/articles/c1d941vw172o?at_medium=RSS&at_campaign=rss",
      "image": "https://ichef.bbci.co.uk/ace/standard/240/cpsprodpb/ef06/live/1fa644b0-2b59-11f1-8c3a-a5a96d0e4227.jpg"
    },
    {
      "id": "brk-20260330-9514b5",
      "type": "breaking",
      "category": "crypto",
      "badge": "Bitcoin",
      "headline": "Bitcoin analysis says $65K 'entry zone' with oil back above $100",
      "excerpt": "Bitcoin continued to surprise some analysts as it held the lower end of its local range despite fresh Iran pressure on macro markets.",
      "source": "CoinTelegraph",
      "date": "30 Mar 2026",
      "timestamp": "2026-03-30T15:43:54Z",
      "url": "https://cointelegraph.com/news/bitcoin-analysis-says-65k-entry-zone-with-oil-back-above-100?utm_source=rss_feed&utm_medium=rss_tag_bitcoin&utm_campaign=rss_partner_inbound",
      "image": "https://images.cointelegraph.com/images/528_aHR0cHM6Ly9zMy5jb2ludGVsZWdyYXBoLmNvbS91cGxvYWRzLzIwMjYtMDMvMDE5ZDNmMjItNWVhNC03ZGQ2LTk4ZTItYWQ4ODg4NzliMmFhLmpwZw==.jpg"
    },
    {
      "id": "brk-20260330-961af8",
      "type": "breaking",
      "category": "crypto",
      "badge": "Bitcoin",
      "headline": "Bitcoin hashrate falls after Iran conflict, HOOD down 16%: Month in charts",
      "excerpt": "Yields for five-year US Treasury bonds are up 4%, putting a damper on Bitcoin price, which has ended the month much where it started.",
      "source": "CoinTelegraph",
      "date": "30 Mar 2026",
      "timestamp": "2026-03-30T14:58:54Z",
      "url": "https://cointelegraph.com/news/bitcoin-hashrate-falls-iran-war-robinhood-month-charts?utm_source=rss_feed&utm_medium=rss_tag_bitcoin&utm_campaign=rss_partner_inbound",
      "image": "https://images.cointelegraph.com/images/528_aHR0cHM6Ly9zMy5jb2ludGVsZWdyYXBoLmNvbS91cGxvYWRzLzIwMjUtMTIvMDE5YjBmNTktNjA4Ny03MzNjLTg4OWYtMGQ2MDhlYzM5ZDEw.jpg"
    },
    {
      "id": "brk-20260330-b5c08e",
      "type": "breaking",
      "category": "crypto",
      "badge": "Bitcoin",
      "headline": "Pierre Rochard warns US regulators over Bitcoin gap in Basel rewrite",
      "excerpt": "Bitcoin Bond Company CEO Pierre Rochard says US regulators\u2019 Basel III revamp cannot quietly decide how banks treat Bitcoin without clearly explaining the rules and evidence behind them.",
      "source": "CoinTelegraph",
      "date": "30 Mar 2026",
      "timestamp": "2026-03-30T10:40:50Z",
      "url": "https://cointelegraph.com/news/bitcoin-basel-iii-capital-proposal-rochard-warning?utm_source=rss_feed&utm_medium=rss_tag_bitcoin&utm_campaign=rss_partner_inbound",
      "image": "https://images.cointelegraph.com/images/528_aHR0cHM6Ly9zMy5jb2ludGVsZWdyYXBoLmNvbS91cGxvYWRzLzIwMjYtMDMvMDE5ZDNkZDgtZDA5Ni03ZDFjLWJkZGYtYWY5YzdhMGYzNmQzLmpwZw==.jpg"
    },
    {
      "id": "icymi-20260330-f2911e",
      "type": "icymi",
      "category": "crypto",
      "badge": "Ethereum",
      "headline": "Ethereum Foundation accelerates 70,000 ETH staking plan after BitMine sale",
      "excerpt": "The Ethereum Foundation deployed $46.2 million in ETH across 11 deposits as it accelerates a 70,000 ETH staking plan.",
      "source": "CoinTelegraph",
      "date": "30 Mar 2026",
      "timestamp": "2026-03-30T09:45:59Z",
      "url": "https://cointelegraph.com/news/ethereum-foundation-stakes-46m-eth-after-bitmine-sale-accelerates-70k-plan?utm_source=rss_feed&utm_medium=rss_tag_altcoin&utm_campaign=rss_partner_inbound",
      "image": "https://images.cointelegraph.com/images/528_aHR0cHM6Ly9zMy5jb2ludGVsZWdyYXBoLmNvbS91cGxvYWRzLzIwMjYtMDMvMDE5ZDNkZGEtMDY1YS03NGM3LTgzNWItNmY0OWFkMmM2Nzg0LmpwZw==.jpg"
    },
    {
      "id": "icymi-20260330-c0750f",
      "type": "icymi",
      "category": "crypto",
      "badge": "Crypto",
      "headline": "Sam Altman\u2019s World Foundation sells $65M in WLD as token hits new lows",
      "excerpt": "World Foundation sold $65 million in WLD as the token hit record lows, with additional supply expected to enter the market.",
      "source": "CoinTelegraph",
      "date": "29 Mar 2026",
      "timestamp": "2026-03-29T13:41:40Z",
      "url": "https://cointelegraph.com/news/sam-altman-world-wld-sale-65m-token-lows?utm_source=rss_feed&utm_medium=rss_tag_altcoin&utm_campaign=rss_partner_inbound",
      "image": "https://images.cointelegraph.com/images/528_aHR0cHM6Ly9zMy5jb2ludGVsZWdyYXBoLmNvbS91cGxvYWRzLzIwMjYtMDMvMDE5ZDM5YTAtOWYzYi03MjhlLTliYTYtZjU5Y2VkMjBiN2FlLmpwZw==.jpg"
    },
    {
      "id": "icymi-20260330-b4f670",
      "type": "icymi",
      "category": "crypto",
      "badge": "Stablecoin",
      "headline": "Crypto open to future US crackdowns without clear rules: Coin Center",
      "excerpt": "The CLARITY Act stalled in the Senate after banks, crypto firms and lawmakers failed to reach an agreement on key provisions like allowing stablecoin yields.",
      "source": "CoinTelegraph",
      "date": "29 Mar 2026",
      "timestamp": "2026-03-29T07:11:46Z",
      "url": "https://cointelegraph.com/news/crypto-future-us-crackdowns-clarity-act?utm_source=rss_feed&utm_medium=rss_tag_regulation&utm_campaign=rss_partner_inbound",
      "image": "https://images.cointelegraph.com/images/528_aHR0cHM6Ly9zMy5jb2ludGVsZWdyYXBoLmNvbS91cGxvYWRzLzIwMjYtMDMvMDE5ZDM4MGQtZDNkNy03NGI3LWI2NGItZmYwNmU2ZDJiNTJkLmpwZw==.jpg"
    },
    {
      "id": "icymi-20260330-6440e3",
      "type": "icymi",
      "category": "crypto",
      "badge": "Crypto",
      "headline": "Canada proposes crypto political donation ban over interference fears",
      "excerpt": "Canada has proposed banning crypto political donations, citing risks that foreign actors could use digital assets to interfere in elections.",
      "source": "CoinTelegraph",
      "date": "29 Mar 2026",
      "timestamp": "2026-03-29T03:24:30Z",
      "url": "https://cointelegraph.com/news/canada-crypto-donation-deepfake-election-ban?utm_source=rss_feed&utm_medium=rss_tag_regulation&utm_campaign=rss_partner_inbound",
      "image": "https://images.cointelegraph.com/images/528_aHR0cHM6Ly9zMy5jb2ludGVsZWdyYXBoLmNvbS91cGxvYWRzLzIwMjYtMDMvMDE5ZDM2YTQtN2RlZS03NDMwLTgyNjgtNjczN2U0MTRhZTExLmpwZw==.jpg"
    },
    {
      "id": "brk-20260330-2b7967",
      "type": "breaking",
      "category": "crypto",
      "badge": "Bitcoin",
      "headline": "Bitcoin hashrate posts first-quarter drop for first time in 6 years as\u2026",
      "excerpt": "The first-quarter decline breaks a long-standing growth trend, but could ultimately support decentralization as public U.S. miners face losing dominance.",
      "source": "CoinDesk",
      "date": "30 Mar 2026",
      "timestamp": "2026-03-30T15:04:14Z",
      "url": "https://www.coindesk.com/markets/2026/03/30/bitcoin-hashrate-posts-first-quarter-drop-for-first-time-in-6-years-as-miners-pivot-to-ai",
      "image": "https://cdn.sanity.io/images/s3y3vcno/production/09c7af12c3ed9c083ddc433486f71cdad7b77bfd-2560x1416.jpg?fm=jpg&w=1920&h=1080&crop=focalpoint&fit=clip"
    },
    {
      "id": "brk-20260330-fecac6",
      "type": "breaking",
      "category": "crypto",
      "badge": "Crypto",
      "headline": "The SEC\u2019s latest crypto guidance still leaves too much unsaid",
      "excerpt": "The regulatory agency\u2019s reset is real, but the new details stop short of the full course correction the industry needs, say Gibson Dunn attorneys.",
      "source": "CoinDesk",
      "date": "30 Mar 2026",
      "timestamp": "2026-03-30T15:00:00Z",
      "url": "https://www.coindesk.com/opinion/2026/03/30/the-sec-s-latest-crypto-guidance-still-leaves-too-much-unsaid",
      "image": "https://cdn.sanity.io/images/s3y3vcno/production/d515099cc27d1cef5d333e5c01bb778ce49d7531-6000x3376.jpg?fm=jpg&w=1920&h=1080&crop=focalpoint&fit=clip"
    },
    {
      "id": "brk-20260330-c0e011",
      "type": "breaking",
      "category": "crypto",
      "badge": "Bitcoin",
      "headline": "Bitmine makes biggest ether purchase in 2026 while other digital asset\u2026",
      "excerpt": "Tom Lee's Ethereum treasury bought more than 71,000 ETH over the past week, remaining the sole large corporate crypto buyer as Strategy broke its 13-week bitcoin purchase streak.",
      "source": "CoinDesk",
      "date": "30 Mar 2026",
      "timestamp": "2026-03-30T14:38:56Z",
      "url": "https://www.coindesk.com/business/2026/03/30/bitmine-makes-biggest-ether-purchase-in-2026-while-other-digital-asset-treasuries-pull-back",
      "image": "https://cdn.sanity.io/images/s3y3vcno/production/1e317956eae4ebfe2722405225dce7dc0b806dbe-1920x1080.jpg?fm=jpg&w=1920&h=1080&crop=focalpoint&fit=clip"
    },
    {
      "id": "brk-20260330-370427",
      "type": "breaking",
      "category": "crypto",
      "badge": "Crypto",
      "headline": "Zcash upside hinges on repricing financial privacy in an AI-driven world\u2026",
      "excerpt": "The crypto asset manager argued rising surveillance and AI could elevate demand for private digital money, positioning Zcash as a mispriced bet on confidentiality.",
      "source": "CoinDesk",
      "date": "30 Mar 2026",
      "timestamp": "2026-03-30T14:18:22Z",
      "url": "https://www.coindesk.com/tech/2026/03/30/zcash-upside-hinges-on-repricing-financial-privacy-in-an-ai-driven-world-grayscale-says",
      "image": "https://cdn.sanity.io/images/s3y3vcno/production/9939a5f1f9a07aff9f031d41bda6ff5fe38ebae4-720x406.jpg?fm=jpg&w=1920&h=1080&crop=focalpoint&fit=clip"
    },
    {
      "id": "icymi-20260330-11df97",
      "type": "icymi",
      "category": "crypto",
      "badge": "Ethereum",
      "headline": "Ethereum Funds Shed $222 Million as Crypto Bill Fears Rattle Investors",
      "excerpt": "Ethereum funds took the biggest hit as Clarity Act fears and macro headwinds pushed crypto outflows to $414 million for the week.",
      "source": "Decrypt",
      "date": "30 Mar 2026",
      "timestamp": "2026-03-30T17:47:37Z",
      "url": "https://decrypt.co/362698/ethereum-funds-shed-222-million-crypto-bill-fears-rattle-investors",
      "image": "https://cdn.decrypt.co/wp-content/uploads/2025/08/ethereum-decrypt-style-07-gID_7.jpg"
    },
    {
      "id": "icymi-20260330-90c1b4",
      "type": "icymi",
      "category": "crypto",
      "badge": "Bitcoin",
      "headline": "Tom Lee's BitMine Adds More Ethereum as Strategy Takes a Break From\u2026",
      "excerpt": "BitMine continued its Ethereum accumulation, adding to its leading ETH treasury while Strategy took a week off from Bitcoin purchases.",
      "source": "Decrypt",
      "date": "30 Mar 2026",
      "timestamp": "2026-03-30T14:45:53Z",
      "url": "https://decrypt.co/362702/tom-lee-bitmine-adds-ethereum-strategy-takes-break-bitcoin-buying",
      "image": "https://cdn.decrypt.co/wp-content/uploads/2025/11/tom-lee-decrypt-style-03-gID_7.jpg"
    },
    {
      "id": "icymi-20260330-b1343f",
      "type": "icymi",
      "category": "crypto",
      "badge": "Bitcoin",
      "headline": "Bitcoin ETFs Bleed $290M as \u2018Risk-Off\u2019 Mood Deepens",
      "excerpt": "Analysts attribute last week's BTC ETF outflows to geopolitical tensions, fading ceasefire hopes, and end-of-quarter rebalancing.",
      "source": "Decrypt",
      "date": "30 Mar 2026",
      "timestamp": "2026-03-30T05:40:46Z",
      "url": "https://decrypt.co/362696/bitcoin-etfs-bleed-290m-as-risk-off-mood-deepens",
      "image": "https://cdn.decrypt.co/wp-content/uploads/2025/10/bitcoin-dollar-decrypt-style-gID_7.jpg"
    },
    {
      "id": "icymi-20260330-5df257",
      "type": "icymi",
      "category": "crypto",
      "badge": "Crypto",
      "headline": "Three Reasons Why Circle\u2019s Stock Is Under Pressure",
      "excerpt": "A yield ban, a rival's audit, and an unresolved legislative clock have left Circle's stock in limbo for the past week.",
      "source": "Decrypt",
      "date": "30 Mar 2026",
      "timestamp": "2026-03-30T04:20:35Z",
      "url": "https://decrypt.co/362694/three-reasons-why-circles-stock-is-under-pressure",
      "image": "https://cdn.decrypt.co/wp-content/uploads/2025/06/USDC-decrypt-style-07-gID_7.png"
    },
    {
      "id": "icymi-20260330-0f9380",
      "type": "icymi",
      "category": "crypto",
      "badge": "Ethereum",
      "headline": "What\u2019s on the Ethereum Roadmap: Glamsterdam, Hegota and Beyond",
      "excerpt": "Ethereum has rolled out a steady stream of upgrades since 2022. Here\u2019s how those changes fit together\u2014and what\u2019s still ahead.",
      "source": "Decrypt",
      "date": "29 Mar 2026",
      "timestamp": "2026-03-29T16:01:04Z",
      "url": "https://decrypt.co/resources/whats-on-ethereum-roadmap-glamsterdam-hegota-beyond",
      "image": "https://cdn.decrypt.co/wp-content/uploads/2019/06/el_classic-gID_7-pID_6.png"
    },
    {
      "id": "icymi-20260330-82633b",
      "type": "icymi",
      "category": "finance",
      "badge": "Finance",
      "headline": "401(k) alternative asset rule proposed by Labor Department",
      "excerpt": "The Department of Labor has proposed a rule to let 401(k) plans more easily include alternative assets such as private equity, cryptocurrencies and real estate.",
      "source": "CNBC",
      "date": "30 Mar 2026",
      "timestamp": "2026-03-30T17:45:35Z",
      "url": "https://www.cnbc.com/2026/03/30/401ks-alternative-investments.html",
      "image": ""
    },
    {
      "id": "icymi-20260330-524f24",
      "type": "icymi",
      "category": "finance",
      "badge": "Finance",
      "headline": "JetBlue Airways raises bag fees as fuel prices soar",
      "excerpt": "Airfare has climbed for routes around the world, driven by higher fuel prices since the U.S. and Israel attacked Iran.",
      "source": "CNBC",
      "date": "30 Mar 2026",
      "timestamp": "2026-03-30T18:00:47Z",
      "url": "https://www.cnbc.com/2026/03/30/jetblue-airways-raises-checked-baggage-fees-as-fuel-prices-soar.html",
      "image": ""
    },
    {
      "id": "icymi-20260330-fa11f8",
      "type": "icymi",
      "category": "finance",
      "badge": "Finance",
      "headline": "All eyes on the S&P 500 after other indexes slip into correction\u2026",
      "excerpt": "In a weekly video to CNBC PRO subscribers, Woods explained the key levels to watch on the S&P 500 if it falls into a correction.",
      "source": "CNBC",
      "date": "30 Mar 2026",
      "timestamp": "2026-03-30T17:12:24Z",
      "url": "https://www.cnbc.com/2026/03/30/watch-the-sp-after-other-indexes-fall-into-correction-says-jay-woods.html",
      "image": ""
    },
    {
      "id": "icymi-20260330-e0624f",
      "type": "icymi",
      "category": "finance",
      "badge": "Oil",
      "headline": "Brent oil heads for record monthly surge as Iran war enters fifth week",
      "excerpt": "Oil prices climbed on Monday after Yemen's Houthis said they had fired missiles at Israel, opening a new front in the U.S.- and Israeli-led conflict with Iran.",
      "source": "CNBC",
      "date": "30 Mar 2026",
      "timestamp": "2026-03-30T17:38:22Z",
      "url": "https://www.cnbc.com/2026/03/30/oil-price-today-wti-brent-yemen-houthis-israel-iran-war.html",
      "image": ""
    },
    {
      "id": "icymi-20260330-7b6588",
      "type": "icymi",
      "category": "africa",
      "badge": "Africa",
      "headline": "News24 | PODCAST | The Lead: You\u2019ve met the \u2018Cat\u2019, but who is Mike van Wyk?",
      "excerpt": "Seasoned broadcast journalist Graeme Raubenheimer brings you The Lead, News24\u2019s definitive podcast for in-depth reporting.",
      "source": "News24",
      "date": "30 Mar 2026",
      "timestamp": "2026-03-30T18:08:08Z",
      "url": "https://www.news24.com/multimedia/podcasts/podcast-the-lead-youve-met-the-cat-but-who-is-mike-van-wyk-20260330-0950",
      "image": ""
    },
    {
      "id": "icymi-20260330-a193f6",
      "type": "icymi",
      "category": "africa",
      "badge": "Africa",
      "headline": "News24 | SA-born billionaire Natie Kirsh sells US restaurant depot for\u2026",
      "excerpt": "Kirsh is selling Jetro Retaurant Depo in the US.",
      "source": "News24",
      "date": "30 Mar 2026",
      "timestamp": "2026-03-30T18:08:08Z",
      "url": "https://www.news24.com/business/companies/sa-born-billionaire-natie-kirsh-sells-restaurant-depot-for-29bn-20260330-0907",
      "image": ""
    },
    {
      "id": "icymi-20260330-abbf31",
      "type": "icymi",
      "category": "africa",
      "badge": "Nigeria",
      "headline": "News24 | WATCH | Anti-\u2018Nigerian king\u2019 marchers torch vehicles, loot shops\u2026",
      "excerpt": "Several vehicles were torched and shops were damaged and looted during a violent march in Buffalo City on Monday, following the stabbing of one of the marchers.",
      "source": "News24",
      "date": "30 Mar 2026",
      "timestamp": "2026-03-30T18:08:08Z",
      "url": "https://www.news24.com/southafrica/crime-and-courts/stabbing-at-march-over-nigerian-king-coronation-sparks-unrest-in-eastern-cape-city-20260330-0699",
      "image": ""
    },
    {
      "id": "icymi-20260330-5a0e76",
      "type": "icymi",
      "category": "africa",
      "badge": "Africa",
      "headline": "News24 | Africa\u2019s nuclear power push faces big obstacles",
      "excerpt": "African countries are turning to nuclear energy to boost power supply and cut emissions. Yet complex financing, long timelines and safety demands mean only a few nations may realistically bring reactors online.",
      "source": "News24",
      "date": "30 Mar 2026",
      "timestamp": "2026-03-30T18:08:08Z",
      "url": "https://www.news24.com/world/africa/africas-nuclear-power-push-faces-big-obstacles-20260330-0997",
      "image": ""
    },
    {
      "id": "icymi-20260330-aa63d8",
      "type": "icymi",
      "category": "africa",
      "badge": "South Africa",
      "headline": "News24 | Can talks save SA\u2019s NHI from a courtroom war?",
      "excerpt": "Health Minister Aaron Motsoaledi has met with the SA Medical Association \u2013 one of the organisations taking him to court over the National Health Insurance Act \u2013 to talk about \u201cthings we have in common\u201d. President Cyril\u2026",
      "source": "News24",
      "date": "30 Mar 2026",
      "timestamp": "2026-03-30T18:08:08Z",
      "url": "https://www.news24.com/southafrica/health-news/can-talks-save-sas-nhi-from-a-courtroom-war-20260330-0871",
      "image": ""
    },
    {
      "id": "icymi-20260330-3276bb",
      "type": "icymi",
      "category": "africa",
      "badge": "Africa",
      "headline": "News24 | Spain closes airspace to US planes involved in war on Iran",
      "excerpt": "Spain has closed its airspace to planes of the United States involved in the US-Israel war on Iran, the latest step in the country\u2019s opposition to the conflict.",
      "source": "News24",
      "date": "30 Mar 2026",
      "timestamp": "2026-03-30T18:08:08Z",
      "url": "https://www.news24.com/world/spain-closes-airspace-to-us-planes-involved-in-war-on-iran-20260330-0876",
      "image": ""
    },
    {
      "id": "brk-20260330-7dbe4d",
      "type": "breaking",
      "category": "finance",
      "badge": "Inflation",
      "headline": "G7 ready to take \u2018necessary measures\u2019 to ensure energy market stability",
      "excerpt": "Jitters in G7 nations as higher energy prices threaten to drive up inflation, damage purchasing power and stunt growth.",
      "source": "Al Jazeera",
      "date": "30 Mar 2026",
      "timestamp": "2026-03-30T16:56:13Z",
      "url": "https://www.aljazeera.com/news/2026/3/30/g7-ready-to-take-necessary-measures-to-ensure-energy-market-stability?traffic_source=rss",
      "image": ""
    },
    {
      "id": "brk-20260330-cb51a7",
      "type": "breaking",
      "category": "usa",
      "badge": "Iran",
      "headline": "\u2018Strait of Hormuz will reopen one way or another\u2019, Rubio tells Al Jazeera",
      "excerpt": "Secretary of State Marco Rubio has told Al Jazeera that the US will not accept Iran\u2019s claim over the Strait of Hormuz.",
      "source": "Al Jazeera",
      "date": "30 Mar 2026",
      "timestamp": "2026-03-30T16:51:19Z",
      "url": "https://www.aljazeera.com/video/newsfeed/2026/3/30/strait-of-hormuz-will-reopen-one-way-or-another-rubio-tells-al-jazeera?traffic_source=rss",
      "image": ""
    },
    {
      "id": "brk-20260330-33e466",
      "type": "breaking",
      "category": "finance",
      "badge": "Oil",
      "headline": "Fire contained after missile attack on oil refinery in Israel\u2019s Haifa",
      "excerpt": "Attack marks second time Oil Refineries facility in northern Israel targeted during US-Israeli war on Iran.",
      "source": "Al Jazeera",
      "date": "30 Mar 2026",
      "timestamp": "2026-03-30T16:25:31Z",
      "url": "https://www.aljazeera.com/news/2026/3/30/fire-contained-after-missile-attack-on-oil-refinery-in-israels-haifa?traffic_source=rss",
      "image": ""
    },
    {
      "id": "brk-20260330-98af9c",
      "type": "breaking",
      "category": "europe",
      "badge": "UK",
      "headline": "UK pro-Palestine activist arrested weeks after being released on bail",
      "excerpt": "Campaigners believe 21-year-old Qesser Zuhrah was arrested over an Instagram post.",
      "source": "Al Jazeera",
      "date": "30 Mar 2026",
      "timestamp": "2026-03-30T16:18:31Z",
      "url": "https://www.aljazeera.com/news/2026/3/30/uk-pro-palestine-activist-arrested-weeks-after-being-released-on-bail?traffic_source=rss",
      "image": ""
    },
    {
      "id": "brk-20260330-91cb80",
      "type": "breaking",
      "category": "africa",
      "badge": "Africa",
      "headline": "Palestine\u2019s Land Day: 50 Years of Resistance",
      "excerpt": "On the 50th Land Day, Al Jazeera\u2019s Hala Al Shami looks into what happened in Palestine on March 30, 1976.",
      "source": "Al Jazeera",
      "date": "30 Mar 2026",
      "timestamp": "2026-03-30T16:14:53Z",
      "url": "https://www.aljazeera.com/video/newsfeed/2026/3/30/palestines-land-day-50-years-of-resistance?traffic_source=rss",
      "image": ""
    },
    {
      "id": "brk-20260330-1fd83e",
      "type": "breaking",
      "category": "finance",
      "badge": "Finance",
      "headline": "We dug up medics in Gaza. A year later, international law remains buried",
      "excerpt": "Israel has created an environment of impunity for attacks on healthcare that has spread well beyond Gaza's borders.",
      "source": "Al Jazeera",
      "date": "30 Mar 2026",
      "timestamp": "2026-03-30T16:13:00Z",
      "url": "https://www.aljazeera.com/opinions/2026/3/30/we-dug-up-medics-in-gaza-a-year-later-international-law-remains-buried?traffic_source=rss",
      "image": ""
    },
    {
      "id": "brk-20260330-4b8685",
      "type": "breaking",
      "category": "finance",
      "badge": "Finance",
      "headline": "Heavy rain, floods kill at least 45 people in Afghanistan, Pakistan",
      "excerpt": "At least 28 people are killed in Afghanistan and 17 in Pakistan after heavy rainfall causes severe flooding.",
      "source": "Al Jazeera",
      "date": "30 Mar 2026",
      "timestamp": "2026-03-30T16:04:49Z",
      "url": "https://www.aljazeera.com/news/2026/3/30/heavy-rain-floods-kill-at-least-45-people-in-afghanistan-pakistan?traffic_source=rss",
      "image": ""
    },
    {
      "id": "brk-20260330-327804",
      "type": "breaking",
      "category": "africa",
      "badge": "Egypt",
      "headline": "Egypt\u2019s president urges Trump to stop war on Iran",
      "excerpt": "Egypt\u2019s President Abdel Fattah el-Sisi has called on Trump to end the war on Iran.",
      "source": "Al Jazeera",
      "date": "30 Mar 2026",
      "timestamp": "2026-03-30T16:01:02Z",
      "url": "https://www.aljazeera.com/video/newsfeed/2026/3/30/egypts-president-urges-trump-to-stop-war-on-iran?traffic_source=rss",
      "image": ""
    },
    {
      "id": "brk-20260330-19b5a2",
      "type": "breaking",
      "category": "usa",
      "badge": "USA",
      "headline": "FIFA World Cup will be held amid \u2018human rights crisis\u2019 in the US: Amnesty",
      "excerpt": "Rights group says football tournament in Canada, Mexico and US poses risks for fans from local communities and abroad.",
      "source": "Al Jazeera",
      "date": "30 Mar 2026",
      "timestamp": "2026-03-30T15:58:13Z",
      "url": "https://www.aljazeera.com/sports/2026/3/30/fifa-world-cup-will-be-held-amid-human-rights-crisis-in-the-us-amnesty?traffic_source=rss",
      "image": ""
    },
    {
      "id": "brk-20260330-068701",
      "type": "breaking",
      "category": "usa",
      "badge": "Politics",
      "headline": "Trump threatens to \u2018blow up\u2019 desalination plants in Iran if no deal reached",
      "excerpt": "Legal expert says targeting civilian sites would be 'collective punishment', which is prohibited under laws of war.",
      "source": "Al Jazeera",
      "date": "30 Mar 2026",
      "timestamp": "2026-03-30T15:51:18Z",
      "url": "https://www.aljazeera.com/news/2026/3/30/trump-threatens-to-blow-up-all-desalination-plants-in-iran?traffic_source=rss",
      "image": ""
    },
    {
      "id": "brk-20260330-d1dba1",
      "type": "breaking",
      "category": "finance",
      "badge": "Finance",
      "headline": "Cardiff City damages claim over Emiliano Sala death dismissed",
      "excerpt": "The club, which was claiming \u00a3104m in compensation, will now have to fork out about \u00a3400,000.",
      "source": "BBC News",
      "date": "30 Mar 2026",
      "timestamp": "2026-03-30T14:24:02Z",
      "url": "https://www.bbc.com/news/articles/c8jkeprrn00o?at_medium=RSS&at_campaign=rss",
      "image": "https://ichef.bbci.co.uk/ace/standard/240/cpsprodpb/900d/live/1c8a9c00-2c39-11f1-a485-4515f7cdb641.jpg"
    },
    {
      "id": "brk-20260330-60ca35",
      "type": "breaking",
      "category": "finance",
      "badge": "Finance",
      "headline": "Fugitive Dezi Freeman shot dead by Australian police after seven months in\u2026",
      "excerpt": "Freeman has been wanted since the fatal shooting of two police officers in Porepunkah in August.",
      "source": "BBC News",
      "date": "30 Mar 2026",
      "timestamp": "2026-03-30T07:07:15Z",
      "url": "https://www.bbc.com/news/articles/c93e4gxn22wo?at_medium=RSS&at_campaign=rss",
      "image": "https://ichef.bbci.co.uk/ace/standard/240/cpsprodpb/3a64/live/ca8a1d30-2bda-11f1-934f-036468834728.png"
    },
    {
      "id": "brk-20260330-a00bdf",
      "type": "breaking",
      "category": "africa",
      "badge": "Africa",
      "headline": "Myanmar junta chief Min Aung Hlaing nominated as president",
      "excerpt": "The military leader, who has been sanctioned by Western countries, is now certain to get the job.",
      "source": "BBC News",
      "date": "30 Mar 2026",
      "timestamp": "2026-03-30T05:26:09Z",
      "url": "https://www.bbc.com/news/articles/clyew40w249o?at_medium=RSS&at_campaign=rss",
      "image": "https://ichef.bbci.co.uk/ace/standard/240/cpsprodpb/823e/live/a40e2430-2bf8-11f1-8c73-bf1bf582fe35.jpg"
    },
    {
      "id": "brk-20260330-bba8ed",
      "type": "breaking",
      "category": "africa",
      "badge": "Nigeria",
      "headline": "Nigerian president's rivals get major boost as political heavyweight joins\u2026",
      "excerpt": "Rabiu Kwankwaso joins the ADC, a coalition poised to take on President Tinubu in the 2027 elections.",
      "source": "BBC News",
      "date": "30 Mar 2026",
      "timestamp": "2026-03-30T16:30:58Z",
      "url": "https://www.bbc.com/news/articles/c2k3vzjp1ylo?at_medium=RSS&at_campaign=rss",
      "image": "https://ichef.bbci.co.uk/ace/standard/240/cpsprodpb/978c/live/ae2bbba0-2c55-11f1-862e-73ba828c2693.jpg"
    },
    {
      "id": "icymi-20260330-d7169b",
      "type": "icymi",
      "category": "africa",
      "badge": "Africa",
      "headline": "'This is bigger than football' - DR Congo bid to end 52-year World Cup wait",
      "excerpt": "DR Congo face Jamaica in a World Cup play-off, hoping to reach the tournament for the first time since 1974, a campaign memorable for the wrong reasons.",
      "source": "BBC Africa",
      "date": "30 Mar 2026",
      "timestamp": "2026-03-30T15:42:03Z",
      "url": "https://www.bbc.com/sport/football/articles/cwyd1zpy81mo?at_medium=RSS&at_campaign=rss",
      "image": "https://ichef.bbci.co.uk/ace/standard/240/cpsprodpb/1cf5/live/a182e0d0-2a08-11f1-b297-95b0a0a8331e.jpg"
    },
    {
      "id": "icymi-20260330-eb0f1d",
      "type": "icymi",
      "category": "africa",
      "badge": "Kenya",
      "headline": "One ant for $220: The new frontier of wildlife trafficking",
      "excerpt": "The craze for collecting ants takes Kenya by surprise as smugglers zone in to make a profit.",
      "source": "BBC Africa",
      "date": "29 Mar 2026",
      "timestamp": "2026-03-29T00:01:15Z",
      "url": "https://www.bbc.com/news/articles/cg4g44zv37qo?at_medium=RSS&at_campaign=rss",
      "image": "https://ichef.bbci.co.uk/ace/standard/240/cpsprodpb/7761/live/aa82d2e0-2a1b-11f1-b297-95b0a0a8331e.jpg"
    },
    {
      "id": "icymi-20260330-c767aa",
      "type": "icymi",
      "category": "africa",
      "badge": "Africa",
      "headline": "Rationing power and diluting petrol - how African countries are coping\u2026",
      "excerpt": "The disruption in oil supplies has caused shortages and concerns in several African countries.",
      "source": "BBC Africa",
      "date": "30 Mar 2026",
      "timestamp": "2026-03-30T11:49:26Z",
      "url": "https://www.bbc.com/news/articles/cq8wkq1n9epo?at_medium=RSS&at_campaign=rss",
      "image": "https://ichef.bbci.co.uk/ace/standard/240/cpsprodpb/0a59/live/e61b7ba0-29bb-11f1-952c-77491ff53aff.jpg"
    },
    {
      "id": "icymi-20260330-4b9f89",
      "type": "icymi",
      "category": "europe",
      "badge": "Germany",
      "headline": "How deepfake porn scandal surrounding TV star rocked Germany",
      "excerpt": "Collien Fernandes has accused her ex-husband of spreading images of her online, but he has categorically denied it.",
      "source": "BBC Europe",
      "date": "29 Mar 2026",
      "timestamp": "2026-03-29T00:00:18Z",
      "url": "https://www.bbc.com/news/articles/c9vlm4j47e2o?at_medium=RSS&at_campaign=rss",
      "image": "https://ichef.bbci.co.uk/ace/standard/240/cpsprodpb/47e0/live/6bc0d8c0-2b4e-11f1-a79a-77e93010d956.jpg"
    },
    {
      "id": "icymi-20260330-63addf",
      "type": "icymi",
      "category": "usa",
      "badge": "USA",
      "headline": "Air Canada CEO to retire after condolence-video controversy",
      "excerpt": "Michael Rousseau faced calls to resign for his English-only message after the fatal Air Canada collision at LaGuardia airport.",
      "source": "BBC News",
      "date": "30 Mar 2026",
      "timestamp": "2026-03-30T13:55:01Z",
      "url": "https://www.bbc.com/news/articles/cgme8xy2rl1o?at_medium=RSS&at_campaign=rss",
      "image": "https://ichef.bbci.co.uk/ace/standard/240/cpsprodpb/a5da/live/17b9c0c0-2c3e-11f1-9d83-af3423d2a1a1.jpg"
    }
  ]
}