{
  "last_updated": "2026-03-26T12:14:34.963178+02:00",
  "articles": [
    {
      "id": "brk-20260326-ce8530",
      "type": "breaking",
      "category": "finance",
      "badge": "Finance",
      "headline": "Israel hinders repair of damaged water infra deepening Gaza\u2019s health crisis",
      "excerpt": "Palestinian engineers struggle to repair Gaza's water system, which has been contaminated, posing a health risk.",
      "source": "Al Jazeera",
      "date": "26 Mar 2026",
      "timestamp": "2026-03-26T09:52:51Z",
      "url": "https://www.aljazeera.com/features/2026/3/26/israel-hinders-repair-of-damaged-water-infra-deepening-gazas-health-crisis?traffic_source=rss",
      "image": ""
    },
    {
      "id": "brk-20260326-9bfb50",
      "type": "breaking",
      "category": "finance",
      "badge": "Finance",
      "headline": "Amid US-Israel war, Iran football team trains in Turkiye before World Cup",
      "excerpt": "Iran will play two friendly matches in Turkiye as they prepare for the FIFA World Cup in the US, Canada and Mexico.",
      "source": "Al Jazeera",
      "date": "26 Mar 2026",
      "timestamp": "2026-03-26T09:48:22Z",
      "url": "https://www.aljazeera.com/sports/2026/3/26/amid-us-israel-war-iran-football-team-trains-in-turkiye-before-world-cup?traffic_source=rss",
      "image": ""
    },
    {
      "id": "brk-20260326-aa1491",
      "type": "breaking",
      "category": "europe",
      "badge": "France",
      "headline": "Brazil vs France: When and where is the match? Will Mbappe, Vinicius play?",
      "excerpt": "French and Brazilian stars in focus as former title holders meet in a glamour friendly in Boston, US, before World Cup.",
      "source": "Al Jazeera",
      "date": "26 Mar 2026",
      "timestamp": "2026-03-26T09:16:40Z",
      "url": "https://www.aljazeera.com/sports/2026/3/26/brazil-vs-france-when-and-where-is-the-match-will-mbappe-vinicius-play?traffic_source=rss",
      "image": ""
    },
    {
      "id": "brk-20260326-b43d60",
      "type": "breaking",
      "category": "usa",
      "badge": "Politics",
      "headline": "Cuban president says Raul Castro involved in US talks amid oil blockade",
      "excerpt": "The talks come amid increasing tensions with the US after Trump said he would be 'honoured' to take over Cuba.",
      "source": "Al Jazeera",
      "date": "26 Mar 2026",
      "timestamp": "2026-03-26T09:09:06Z",
      "url": "https://www.aljazeera.com/news/2026/3/26/cuban-president-says-raul-castro-involved-in-us-talks-amid-oil-blockade?traffic_source=rss",
      "image": ""
    },
    {
      "id": "brk-20260326-6bfea9",
      "type": "breaking",
      "category": "usa",
      "badge": "USA",
      "headline": "Venezuela\u2019s Maduro set to appear in US court months after abduction",
      "excerpt": "The Venezuelan leader, who is accused of plotting to traffic cocaine, denies all charges as part of an imperialist plot.",
      "source": "Al Jazeera",
      "date": "26 Mar 2026",
      "timestamp": "2026-03-26T08:57:01Z",
      "url": "https://www.aljazeera.com/news/2026/3/26/venezuelas-maduro-set-to-appear-in-us-court-months-after-abduction?traffic_source=rss",
      "image": ""
    },
    {
      "id": "brk-20260326-0f09a0",
      "type": "breaking",
      "category": "africa",
      "badge": "Forex",
      "headline": "\u2018He will call me Mama\u2019: The Gaza \u2018grandmother\u2019 raising an orphaned baby",
      "excerpt": "Maha was 'Grandmother' in her family until she adopted Hamza, born the day an Israeli air strike killed his parents.",
      "source": "Al Jazeera",
      "date": "26 Mar 2026",
      "timestamp": "2026-03-26T08:53:33Z",
      "url": "https://www.aljazeera.com/features/longform/2026/3/26/he-will-call-me-mama-the-gaza-grandmother-raising-an-orphaned-baby?traffic_source=rss",
      "image": ""
    },
    {
      "id": "brk-20260326-f1e48a",
      "type": "breaking",
      "category": "africa",
      "badge": "Africa",
      "headline": "Prepare for turbulence - how a prolonged Middle East conflict could\u2026",
      "excerpt": "The Gulf's hub airports made long-distance travel cheaper - but now their future looks unclear.",
      "source": "BBC News",
      "date": "26 Mar 2026",
      "timestamp": "2026-03-26T00:41:16Z",
      "url": "https://www.bbc.com/news/articles/cn08x9lw0pzo?at_medium=RSS&at_campaign=rss",
      "image": "https://ichef.bbci.co.uk/ace/standard/240/cpsprodpb/1543/live/c1c12910-2837-11f1-b297-95b0a0a8331e.jpg"
    },
    {
      "id": "brk-20260326-7d877b",
      "type": "breaking",
      "category": "usa",
      "badge": "Conflict",
      "headline": "Campaigners welcome Meta and YouTube's defeat in landmark social media\u2026",
      "excerpt": "A woman has been awarded $6m in a verdict that could have implications for hundreds of other cases in the US.",
      "source": "BBC News",
      "date": "26 Mar 2026",
      "timestamp": "2026-03-26T09:43:25Z",
      "url": "https://www.bbc.com/news/articles/c747x7gz249o?at_medium=RSS&at_campaign=rss",
      "image": "https://ichef.bbci.co.uk/ace/standard/240/cpsprodpb/9830/live/9e8aadf0-28e0-11f1-934f-036468834728.jpg"
    },
    {
      "id": "brk-20260326-848e1a",
      "type": "breaking",
      "category": "finance",
      "badge": "Finance",
      "headline": "New India bill to amend transgender rights sparks protests",
      "excerpt": "The bill seeks to change how transgender people are legally recognised and their right to self-identify.",
      "source": "BBC News",
      "date": "26 Mar 2026",
      "timestamp": "2026-03-26T09:01:03Z",
      "url": "https://www.bbc.com/news/articles/czx9de4ygl7o?at_medium=RSS&at_campaign=rss",
      "image": "https://ichef.bbci.co.uk/ace/standard/240/cpsprodpb/0c5a/live/49ff9df0-28d5-11f1-b961-17333222d025.jpg"
    },
    {
      "id": "brk-20260326-040759",
      "type": "breaking",
      "category": "usa",
      "badge": "Politics",
      "headline": "Trump confirms May meeting with Xi Jinping as Iran war forces postponement",
      "excerpt": "Trump's delayed meeting with Xi Jinping will be the first visit to China by a US president since 2017.",
      "source": "BBC News",
      "date": "26 Mar 2026",
      "timestamp": "2026-03-26T07:34:55Z",
      "url": "https://www.bbc.com/news/articles/c05dpr1m71go?at_medium=RSS&at_campaign=rss",
      "image": "https://ichef.bbci.co.uk/ace/standard/240/cpsprodpb/fef7/live/33194d00-28af-11f1-bb58-f7787f04c8ed.jpg"
    },
    {
      "id": "brk-20260326-1c2b70",
      "type": "breaking",
      "category": "finance",
      "badge": "Finance",
      "headline": "Australia's sunscreen regulator wants new rules after recent product\u2026",
      "excerpt": "The medicines regulator is proposing stricter rules after more than a dozen products were recalled.",
      "source": "BBC News",
      "date": "26 Mar 2026",
      "timestamp": "2026-03-26T05:45:39Z",
      "url": "https://www.bbc.com/news/articles/cql75nx0e0yo?at_medium=RSS&at_campaign=rss",
      "image": "https://ichef.bbci.co.uk/ace/standard/240/cpsprodpb/e5af/live/3d61ffd0-28cf-11f1-9dbb-e16c14c0783a.jpg"
    },
    {
      "id": "brk-20260326-63497c",
      "type": "breaking",
      "category": "africa",
      "badge": "Africa",
      "headline": "Parents should monitor children '24/7' on Roblox, says developer",
      "excerpt": "Roblox said safety was a top priority and it had advanced safeguards in place to keep users safe.",
      "source": "BBC News",
      "date": "26 Mar 2026",
      "timestamp": "2026-03-26T00:31:33Z",
      "url": "https://www.bbc.com/news/articles/cd6l07wwvlpo?at_medium=RSS&at_campaign=rss",
      "image": "https://ichef.bbci.co.uk/ace/standard/240/cpsprodpb/a8a7/live/4ba1f300-2877-11f1-831a-89df8c4bf49f.jpg"
    },
    {
      "id": "brk-20260326-92f596",
      "type": "breaking",
      "category": "finance",
      "badge": "Oil",
      "headline": "'We are being choked': Philippines transport workers strike over fuel costs",
      "excerpt": "It comes as a ship carrying barrels of Russian crude oil arrived in the Philippines earlier this week.",
      "source": "BBC News",
      "date": "26 Mar 2026",
      "timestamp": "2026-03-26T09:00:31Z",
      "url": "https://www.bbc.com/news/articles/c4glxn24gd6o?at_medium=RSS&at_campaign=rss",
      "image": "https://ichef.bbci.co.uk/ace/standard/240/cpsprodpb/e059/live/e7e726b0-28c5-11f1-9516-876fae3988b5.jpg"
    },
    {
      "id": "icymi-20260326-596ec8",
      "type": "icymi",
      "category": "africa",
      "badge": "Africa",
      "headline": "Senegal appeal to be heard 'as swiftly as possible'",
      "excerpt": "The Court of Arbitration for Sport (Cas) says it will rule on Senegal's appeal against being stripped of the Africa Cup of Nations title \"as swiftly as possible\".",
      "source": "BBC Africa",
      "date": "25 Mar 2026",
      "timestamp": "2026-03-25T16:50:20Z",
      "url": "https://www.bbc.com/sport/football/articles/c895x5x0jy5o?at_medium=RSS&at_campaign=rss",
      "image": "https://ichef.bbci.co.uk/ace/standard/240/cpsprodpb/acca/live/10b7b220-2868-11f1-aa48-117dee2050d3.jpg"
    },
    {
      "id": "icymi-20260326-f5bdea",
      "type": "icymi",
      "category": "africa",
      "badge": "Africa",
      "headline": "Saudi Pro League, the US or Europe - what are Salah's options?",
      "excerpt": "Liverpool reporter Aadam Patel analyses what Mohamed Salah's next move might be following the forward's announcement that he is to leave the club this summer.",
      "source": "BBC Africa",
      "date": "25 Mar 2026",
      "timestamp": "2026-03-25T14:50:13Z",
      "url": "https://www.bbc.com/sport/football/articles/c86ew5d52d9o?at_medium=RSS&at_campaign=rss",
      "image": "https://ichef.bbci.co.uk/ace/standard/240/cpsprodpb/3de4/live/c8f06f40-2849-11f1-923f-8be7c886ebd4.jpg"
    },
    {
      "id": "icymi-20260326-e3df82",
      "type": "icymi",
      "category": "europe",
      "badge": "UK",
      "headline": "UK now 'ready' to seize Russian shadow fleet ships, Healey says",
      "excerpt": "Forces are now approved to board sanctioned vessels if required, after ministers identified a legal basis in January.",
      "source": "BBC Europe",
      "date": "26 Mar 2026",
      "timestamp": "2026-03-26T10:04:58Z",
      "url": "https://www.bbc.com/news/articles/cvg0n9z3jlvo?at_medium=RSS&at_campaign=rss",
      "image": "https://ichef.bbci.co.uk/ace/standard/240/cpsprodpb/0269/live/c6bee1a0-28eb-11f1-a79a-77e93010d956.jpg"
    },
    {
      "id": "icymi-20260326-c21638",
      "type": "icymi",
      "category": "europe",
      "badge": "Europe",
      "headline": "Danish PM fails to secure majority in party's weakest election showing\u2026",
      "excerpt": "The party, which has been in power since 2019, gained the most votes but faces tough talks on forming a new government.",
      "source": "BBC Europe",
      "date": "25 Mar 2026",
      "timestamp": "2026-03-25T07:59:41Z",
      "url": "https://www.bbc.com/news/articles/c74v5qynl9vo?at_medium=RSS&at_campaign=rss",
      "image": "https://ichef.bbci.co.uk/ace/standard/240/cpsprodpb/c11e/live/e4f3d790-2826-11f1-934f-036468834728.jpg"
    },
    {
      "id": "icymi-20260326-2aece1",
      "type": "icymi",
      "category": "usa",
      "badge": "USA",
      "headline": "Houston airport wait times reach over four hours amid US travel chaos",
      "excerpt": "Nearly 40% of the security staff at the George Bush airport did not show up - the highest such rate in the country, US media report.",
      "source": "BBC News",
      "date": "26 Mar 2026",
      "timestamp": "2026-03-26T02:56:17Z",
      "url": "https://www.bbc.com/news/articles/c239vyp2n35o?at_medium=RSS&at_campaign=rss",
      "image": "https://ichef.bbci.co.uk/ace/standard/240/cpsprodpb/16c1/live/546cea30-28bd-11f1-a2eb-6535cf48865c.jpg"
    },
    {
      "id": "icymi-20260326-3a3fd0",
      "type": "icymi",
      "category": "usa",
      "badge": "USA",
      "headline": "Rocket stocks soar on report Musk's SpaceX to file for share sale",
      "excerpt": "Reports it plans the biggest listing ever sent the shares of firms in its orbit soaring in US trade on Wednesday.",
      "source": "BBC News",
      "date": "26 Mar 2026",
      "timestamp": "2026-03-26T02:01:39Z",
      "url": "https://www.bbc.com/news/articles/c5y8d721q18o?at_medium=RSS&at_campaign=rss",
      "image": "https://ichef.bbci.co.uk/ace/standard/240/cpsprodpb/a653/live/74eea880-28b7-11f1-a969-25e19bf2e998.jpg"
    },
    {
      "id": "icymi-20260326-57da56",
      "type": "icymi",
      "category": "usa",
      "badge": "USA",
      "headline": "'We are in agony' - Savannah Guthrie does first interview since mum's\u2026",
      "excerpt": "The US presenter says terrifying thoughts wake her at night as she imagines what happened.",
      "source": "BBC News",
      "date": "25 Mar 2026",
      "timestamp": "2026-03-25T16:38:03Z",
      "url": "https://www.bbc.com/news/articles/ckgxzlny4w3o?at_medium=RSS&at_campaign=rss",
      "image": "https://ichef.bbci.co.uk/ace/standard/240/cpsprodpb/c676/live/4eecea00-2850-11f1-937e-1d8f354c3b9a.jpg"
    },
    {
      "id": "icymi-20260326-166bbc",
      "type": "icymi",
      "category": "finance",
      "badge": "Markets",
      "headline": "UK forecast to face weaker growth and higher inflation from Iran war",
      "excerpt": "The OECD downgrades forecasts for many of the world's biggest economies due to the US-Israel war with Iran.",
      "source": "BBC Business",
      "date": "26 Mar 2026",
      "timestamp": "2026-03-26T10:12:09Z",
      "url": "https://www.bbc.com/news/articles/cgk0j71g417o?at_medium=RSS&at_campaign=rss",
      "image": "https://ichef.bbci.co.uk/ace/standard/240/cpsprodpb/4853/live/a28db640-28f9-11f1-a79a-77e93010d956.jpg"
    },
    {
      "id": "icymi-20260326-7cfa29",
      "type": "icymi",
      "category": "finance",
      "badge": "Finance",
      "headline": "'The era of impunity is over': What next for big tech after landmark\u2026",
      "excerpt": "The ruling could be the beginning of the end of social media as we know it, writes the BBC Technology Editor Zoe Kleinman.",
      "source": "BBC Business",
      "date": "26 Mar 2026",
      "timestamp": "2026-03-26T09:37:57Z",
      "url": "https://www.bbc.com/news/articles/c87wd0d84jqo?at_medium=RSS&at_campaign=rss",
      "image": "https://ichef.bbci.co.uk/ace/standard/240/cpsprodpb/57c0/live/feb5be00-28f8-11f1-a95f-75471ca6e71e.jpg"
    },
    {
      "id": "icymi-20260326-13eb96",
      "type": "icymi",
      "category": "finance",
      "badge": "Finance",
      "headline": "Octopus boss: We've seen a 50% rise in solar panel sales since start of\u2026",
      "excerpt": "The UK giant is optimistic but chief executive Greg Jackson tells the BBC he is making contingency plans.",
      "source": "BBC Business",
      "date": "26 Mar 2026",
      "timestamp": "2026-03-26T00:00:49Z",
      "url": "https://www.bbc.com/news/articles/c4gjlezq80no?at_medium=RSS&at_campaign=rss",
      "image": "https://ichef.bbci.co.uk/ace/standard/240/cpsprodpb/e0c8/live/8ea0abf0-2882-11f1-b297-95b0a0a8331e.jpg"
    },
    {
      "id": "icymi-20260326-31613f",
      "type": "icymi",
      "category": "finance",
      "badge": "Finance",
      "headline": "The homeless teenager who became a successful advertising boss",
      "excerpt": "Greg Daily has swapped sleeping on friends' sofas for running a popular digital marketing company.",
      "source": "BBC Business",
      "date": "26 Mar 2026",
      "timestamp": "2026-03-26T00:03:36Z",
      "url": "https://www.bbc.com/news/articles/cn08lx745ndo?at_medium=RSS&at_campaign=rss",
      "image": "https://ichef.bbci.co.uk/ace/standard/240/cpsprodpb/f116/live/62b5ab20-2761-11f1-8dfa-e79b06fb69fd.jpg"
    },
    {
      "id": "icymi-20260326-69fa6c",
      "type": "icymi",
      "category": "finance",
      "badge": "Finance",
      "headline": "UK CO2 plant to reopen in Iran war contingency plan",
      "excerpt": "The government will invest \u00a3100m to restart the Teesside site producing carbon dioxide, a key part of food and drink manufacturing.",
      "source": "BBC Business",
      "date": "26 Mar 2026",
      "timestamp": "2026-03-26T09:55:18Z",
      "url": "https://www.bbc.com/news/articles/cew7xrj4497o?at_medium=RSS&at_campaign=rss",
      "image": "https://ichef.bbci.co.uk/ace/standard/240/cpsprodpb/9e92/live/24bf6d00-28b6-11f1-b297-95b0a0a8331e.jpg"
    },
    {
      "id": "brk-20260326-4d99e0",
      "type": "breaking",
      "category": "crypto",
      "badge": "Bitcoin",
      "headline": "$18.6B in Bitcoin options expire Friday: Should traders prepare for $75K\u2026",
      "excerpt": "Bitcoin bulls face an uphill battle to turn the March options expiry in their favor, requiring a 6% price rally to $75,000 before Friday.",
      "source": "CoinTelegraph",
      "date": "26 Mar 2026",
      "timestamp": "2026-03-26T00:31:28Z",
      "url": "https://cointelegraph.com/news/18-6b-in-bitcoin-options-expire-friday-should-traders-prepare-for-75k-btc?utm_source=rss_feed&utm_medium=rss_tag_bitcoin&utm_campaign=rss_partner_inbound",
      "image": "https://images.cointelegraph.com/images/528_aHR0cHM6Ly9zMy5jb2ludGVsZWdyYXBoLmNvbS91cGxvYWRzLzIwMjYtMDMvMDE5Y2IxZjktNzNiYS03ZmRkLWI3YmMtZjIyMzc2MWNjZTJhLmpwZw==.jpg"
    },
    {
      "id": "brk-20260326-486793",
      "type": "breaking",
      "category": "crypto",
      "badge": "Bitcoin",
      "headline": "Bitcoin \u2018compression\u2019 outcome may send BTC to $80K: Analyst",
      "excerpt": "Bitcoin charts point to a possible rally to $80,000, but spot volumes need to increase in order for the rally to hold.",
      "source": "CoinTelegraph",
      "date": "25 Mar 2026",
      "timestamp": "2026-03-25T19:58:14Z",
      "url": "https://cointelegraph.com/news/bitcoin-compression-outcome-may-send-btc-to-dollar80k-analyst?utm_source=rss_feed&utm_medium=rss_tag_bitcoin&utm_campaign=rss_partner_inbound",
      "image": "https://images.cointelegraph.com/images/528_aHR0cHM6Ly9zMy5jb2ludGVsZWdyYXBoLmNvbS91cGxvYWRzLzIwMjUtMTIvMDE5YjM1ZDItMWRkZS03NGQxLTlmOWYtMjY1ZWVjNDU0ZTBiLmpwZw==.jpg"
    },
    {
      "id": "brk-20260326-6dc46a",
      "type": "breaking",
      "category": "crypto",
      "badge": "Bitcoin",
      "headline": "Bitcoin retakes $71K as US sends Iran 15-point ceasefire plan",
      "excerpt": "Bitcoin bounced back above $71,000 after US President Donald Trump\u2019s administration sent a proposal to Iran aimed at ending the war.",
      "source": "CoinTelegraph",
      "date": "25 Mar 2026",
      "timestamp": "2026-03-25T10:54:33Z",
      "url": "https://cointelegraph.com/news/bitcoin-retakes-71k-us-sends-iran-15-point-ceasefire-plan?utm_source=rss_feed&utm_medium=rss_tag_bitcoin&utm_campaign=rss_partner_inbound",
      "image": "https://images.cointelegraph.com/images/528_aHR0cHM6Ly9zMy5jb2ludGVsZWdyYXBoLmNvbS91cGxvYWRzLzIwMjUtMTIvMDE5YWUxZTAtZjEyMy03ZTc1LTljNzAtOThjY2E1NGZmNGI0.jpg"
    },
    {
      "id": "brk-20260326-76f326",
      "type": "breaking",
      "category": "crypto",
      "badge": "Bitcoin",
      "headline": "Bitcoin exchange outflows show \u2018genuine accumulation by investors\u2019: Analyst",
      "excerpt": "Ongoing accumulation of Bitcoin is likely one of the factors behind why the cryptocurrency is trading in a tight range, say crypto analysts.",
      "source": "CoinTelegraph",
      "date": "25 Mar 2026",
      "timestamp": "2026-03-25T05:50:51Z",
      "url": "https://cointelegraph.com/news/persistent-btc-exchange-outflow-suggests-genuine-accumulation-by-investors-analyst?utm_source=rss_feed&utm_medium=rss_tag_bitcoin&utm_campaign=rss_partner_inbound",
      "image": "https://images.cointelegraph.com/images/528_aHR0cHM6Ly9zMy5jb2ludGVsZWdyYXBoLmNvbS91cGxvYWRzLzIwMjYtMDEvMDE5YmMxMGYtMzk4Zi03MTAyLWE2ODUtY2VhZmYyY2ZjOTAyLmpwZw==.jpg"
    },
    {
      "id": "icymi-20260326-7f845f",
      "type": "icymi",
      "category": "crypto",
      "badge": "Ethereum",
      "headline": "Data points to accelerating Ether supply crunch: Will ETH price follow?",
      "excerpt": "The number of Ether staked continues to rise while ETH outflows from exchanges are increasing. Will the phenomenon have a positive or negative impact on ETH price?",
      "source": "CoinTelegraph",
      "date": "25 Mar 2026",
      "timestamp": "2026-03-25T21:15:00Z",
      "url": "https://cointelegraph.com/news/data-points-to-accelerating-ether-supply-crunch-will-eth-price-follow?utm_source=rss_feed&utm_medium=rss_tag_altcoin&utm_campaign=rss_partner_inbound",
      "image": "https://images.cointelegraph.com/images/528_aHR0cHM6Ly9zMy5jb2ludGVsZWdyYXBoLmNvbS91cGxvYWRzLzIwMjYtMDEvMDE5YmRiYzUtYzY2ZS03OWI5LWJhZWQtNDU2OGRhYzU0Y2MzLmpwZw==.jpg"
    },
    {
      "id": "icymi-20260326-6a9d2e",
      "type": "icymi",
      "category": "crypto",
      "badge": "Stablecoin",
      "headline": "AI and stablecoins are winning despite 2026 crypto market slump",
      "excerpt": "Data shows AI tokens and stablecoins held up better than other crypto sectors in 2026, with growth tied to usage, liquidity and infrastructure demand.",
      "source": "CoinTelegraph",
      "date": "24 Mar 2026",
      "timestamp": "2026-03-24T12:29:36Z",
      "url": "https://cointelegraph.com/news/ai-and-stablecoins-winning-despite-2026-crypto-market-slump?utm_source=rss_feed&utm_medium=rss_tag_altcoin&utm_campaign=rss_partner_inbound",
      "image": "https://images.cointelegraph.com/images/528_aHR0cHM6Ly9zMy5jb2ludGVsZWdyYXBoLmNvbS91cGxvYWRzLzIwMjYtMDMvMDE5ZDFmN2EtNTY4NS03NjVhLTg1N2ItOTc3NTBjMTM0YTk4LmpwZw==.jpg"
    },
    {
      "id": "icymi-20260326-81e98b",
      "type": "icymi",
      "category": "crypto",
      "badge": "Crypto",
      "headline": "UK pushes ahead with temporary ban on political crypto donations",
      "excerpt": "The government plans to implement the ban by amending the Representation of the People Bill, with changes taking \"retrospective effect\" from Wednesday.",
      "source": "CoinTelegraph",
      "date": "26 Mar 2026",
      "timestamp": "2026-03-26T06:07:46Z",
      "url": "https://cointelegraph.com/news/uk-forges-ahead-political-crypto-donations-ban?utm_source=rss_feed&utm_medium=rss_tag_regulation&utm_campaign=rss_partner_inbound",
      "image": "https://images.cointelegraph.com/images/528_aHR0cHM6Ly9zMy5jb2ludGVsZWdyYXBoLmNvbS91cGxvYWRzLzIwMjYtMDIvMDE5Yzk3MTUtNmFkZi03ZGRkLTllYjEtZDk1NTFjZWUyMmZkLmpwZw==.jpg"
    },
    {
      "id": "icymi-20260326-efc196",
      "type": "icymi",
      "category": "crypto",
      "badge": "Crypto",
      "headline": "Proposed bill seeks to ban US president, Congress from prediction markets",
      "excerpt": "The bill adds to a wave of recent legislative and state-level actions targeting prediction markets as scrutiny over sports betting, war contracts and alleged insider trading builds.",
      "source": "CoinTelegraph",
      "date": "26 Mar 2026",
      "timestamp": "2026-03-26T05:38:13Z",
      "url": "https://cointelegraph.com/news/lawmakers-introduce-bill-banning-congress-president-from-prediction-markets?utm_source=rss_feed&utm_medium=rss_tag_regulation&utm_campaign=rss_partner_inbound",
      "image": "https://images.cointelegraph.com/images/528_aHR0cHM6Ly9zMy5jb2ludGVsZWdyYXBoLmNvbS91cGxvYWRzLzIwMjYtMDEvMDE5YmJmMTUtZTYwNy03N2QzLTkwZjktYjY4OWQ5YWJjN2JjLmpwZw==.jpg"
    },
    {
      "id": "icymi-20260326-a756c1",
      "type": "icymi",
      "category": "crypto",
      "badge": "Regulation",
      "headline": "US lawmakers hash out tokenized securities concerns in latest hearing",
      "excerpt": "Industry executives told US lawmakers that existing investor protection and financial surveillance regulations should apply to tokenized securities.",
      "source": "CoinTelegraph",
      "date": "25 Mar 2026",
      "timestamp": "2026-03-25T21:12:45Z",
      "url": "https://cointelegraph.com/news/us-lawmakers-tokenized-securities-concerns?utm_source=rss_feed&utm_medium=rss_tag_regulation&utm_campaign=rss_partner_inbound",
      "image": "https://images.cointelegraph.com/images/528_aHR0cHM6Ly9zMy5jb2ludGVsZWdyYXBoLmNvbS91cGxvYWRzLzIwMjYtMDIvMDE5Yzk2MWMtODBiMS03NGFlLThjZDUtMDRkZjBlMzUzNDk0LmpwZw==.jpg"
    },
    {
      "id": "icymi-20260326-089de6",
      "type": "icymi",
      "category": "crypto",
      "badge": "Crypto",
      "headline": "UK review recommends crypto donation pause over foreign interference risk",
      "excerpt": "A UK review led by Philip Rycroft recommended a temporary moratorium on crypto political donations until stronger safeguards and statutory guidance are in place.",
      "source": "CoinTelegraph",
      "date": "25 Mar 2026",
      "timestamp": "2026-03-25T13:46:46Z",
      "url": "https://cointelegraph.com/news/uk-crypto-donation-pause-foreign-interference-risk?utm_source=rss_feed&utm_medium=rss_tag_regulation&utm_campaign=rss_partner_inbound",
      "image": "https://images.cointelegraph.com/images/528_aHR0cHM6Ly9zMy5jb2ludGVsZWdyYXBoLmNvbS91cGxvYWRzLzIwMjYtMDMvMDE5Y2JkN2ItYmY4ZC03NmUxLWEyMzYtMjQxZmZmNGU1YzQxLmpwZw==.jpg"
    },
    {
      "id": "icymi-20260326-2a707a",
      "type": "icymi",
      "category": "crypto",
      "badge": "Crypto",
      "headline": "ECB targets summer for digital euro standards: Cipollone",
      "excerpt": "The ECB\u2019s Piero Cipollone said the central bank wants key technical standards for a possible digital euro locked in by this summer so banks and merchants can prepare for the rollout.",
      "source": "CoinTelegraph",
      "date": "25 Mar 2026",
      "timestamp": "2026-03-25T10:57:51Z",
      "url": "https://cointelegraph.com/news/ecb-targets-summer-digital-euro-standards?utm_source=rss_feed&utm_medium=rss_tag_regulation&utm_campaign=rss_partner_inbound",
      "image": "https://images.cointelegraph.com/images/528_aHR0cHM6Ly9zMy5jb2ludGVsZWdyYXBoLmNvbS91cGxvYWRzLzIwMjUtMTIvMDE5YjM1ZDMtNGQwYy03YjNlLWJlMDctMWYyY2NmMGY3MzAzLmpwZw==.jpg"
    },
    {
      "id": "icymi-20260326-2c596c",
      "type": "icymi",
      "category": "crypto",
      "badge": "Crypto",
      "headline": "CFTC chief launches innovation task force focused on crypto framework",
      "excerpt": "The task force will work with industry participants to develop regulatory approaches for crypto, AI and prediction markets.",
      "source": "CoinTelegraph",
      "date": "24 Mar 2026",
      "timestamp": "2026-03-24T19:32:03Z",
      "url": "https://cointelegraph.com/news/cftc-innovation-task-force-crypto-framework?utm_source=rss_feed&utm_medium=rss_tag_regulation&utm_campaign=rss_partner_inbound",
      "image": "https://images.cointelegraph.com/images/528_aHR0cHM6Ly9zMy5jb2ludGVsZWdyYXBoLmNvbS91cGxvYWRzLzIwMjUtMTIvMDE5YjEwZGQtYmVkYy03MjJhLTlmNGMtOTAzYTc2NTQ3YWNi.jpg"
    },
    {
      "id": "brk-20260326-8386b2",
      "type": "breaking",
      "category": "crypto",
      "badge": "Bitcoin",
      "headline": "Bitcoin has traded in a tight range for nearly 50 days \u2013 but this is not a\u2026",
      "excerpt": "Extended range-bound price action signals structural consolidation rather than a textbook bearish continuation, despite rising downside risks.",
      "source": "CoinDesk",
      "date": "26 Mar 2026",
      "timestamp": "2026-03-26T10:09:10Z",
      "url": "https://www.coindesk.com/markets/2026/03/26/bitcoin-has-traded-in-a-tight-range-for-nearly-50-days-but-this-is-not-a-bear-flag",
      "image": "https://cdn.sanity.io/images/s3y3vcno/production/9db110182f9733ea754c6a9cbd935ad51195b2b4-1920x1080.jpg?fm=jpg&w=1920&h=1080&crop=focalpoint&fit=clip"
    },
    {
      "id": "brk-20260326-f2ee30",
      "type": "breaking",
      "category": "crypto",
      "badge": "Bitcoin",
      "headline": "Bitcoin DAT trade is concentrating in Michael Saylor\u2019s Strategy as\u2026",
      "excerpt": "Strategy accounted for nearly all recent BTC digital-asset treasury purchases, with other firms\u2019 share dropping from 95% to about 2%, CryptoQuant data show.",
      "source": "CoinDesk",
      "date": "26 Mar 2026",
      "timestamp": "2026-03-26T09:20:04Z",
      "url": "https://www.coindesk.com/markets/2026/03/26/michael-saylor-s-strategy-dominates-dat-bitcoin-buying-as-treasury-demand-collapses",
      "image": "https://cdn.sanity.io/images/s3y3vcno/production/a57323d92b3fa599df2ee442af800248477423c0-6000x3376.jpg?fm=jpg&w=1920&h=1080&crop=focalpoint&fit=clip"
    },
    {
      "id": "brk-20260326-1113d7",
      "type": "breaking",
      "category": "crypto",
      "badge": "Crypto",
      "headline": "BitGo teams with ZKsync to build tokenized deposit infrastructure to bring\u2026",
      "excerpt": "Now in testing, the platform aims to enable programmable payments and simplify blockchain adoption for financial institutions.",
      "source": "CoinDesk",
      "date": "25 Mar 2026",
      "timestamp": "2026-03-25T20:00:00Z",
      "url": "https://www.coindesk.com/business/2026/03/25/bitgo-teams-with-zksync-to-build-tokenized-deposit-infrastructure-to-bring-banks-onchain",
      "image": "https://cdn.sanity.io/images/s3y3vcno/production/cc9f0df2f256d6ca65cc434680be96c3248989f5-1536x1098.jpg?fm=jpg&w=1920&h=1080&crop=focalpoint&fit=clip"
    },
    {
      "id": "brk-20260326-d2affd",
      "type": "breaking",
      "category": "crypto",
      "badge": "Crypto",
      "headline": "Crypto Long & Short: Prediction Markets Don\u2019t Just Forecast Power - They\u2026",
      "excerpt": "In this week\u2019s Crypto Long & Short Newsletter, Ryan Kirkley writes on how crypto prediction markets can risk incentivizing manipulation and amplify misinformation at scale.",
      "source": "CoinDesk",
      "date": "25 Mar 2026",
      "timestamp": "2026-03-25T18:36:03Z",
      "url": "https://www.coindesk.com/coindesk-indices/2026/03/25/crypto-long-and-short-prediction-markets-don-t-just-forecast-power-they-reshape-it",
      "image": "https://cdn.sanity.io/images/s3y3vcno/production/c934d6c2d29fe578ea58a3b7b37cac4c540b80be-7008x4672.jpg?fm=jpg&w=1920&h=1080&crop=focalpoint&fit=clip"
    },
    {
      "id": "brk-20260326-fc2c1a",
      "type": "breaking",
      "category": "crypto",
      "badge": "Crypto",
      "headline": "AI agents to help investigators unearth crypto criminals, according to new\u2026",
      "excerpt": "TRM Labs has added an AI agent to the services the blockchain analytics firm offers law enforcement agencies.",
      "source": "CoinDesk",
      "date": "25 Mar 2026",
      "timestamp": "2026-03-25T18:24:17Z",
      "url": "https://www.coindesk.com/policy/2026/03/25/ai-agents-to-help-investigators-unearth-crypto-criminals-according-to-new-trm-program",
      "image": "https://cdn.sanity.io/images/s3y3vcno/production/96ddd9de4292483cec1d6ed536bf195e99c12f02-2560x1440.jpg?fm=jpg&w=1920&h=1080&crop=focalpoint&fit=clip"
    },
    {
      "id": "icymi-20260326-05b319",
      "type": "icymi",
      "category": "crypto",
      "badge": "Crypto",
      "headline": "Australia Lays Groundwork for Tokenized Asset Markets After RBA Project",
      "excerpt": "Regulators are beginning work on legal and market infrastructure for tokenized assets, moving from pilot programs to real-world implementation.",
      "source": "Decrypt",
      "date": "26 Mar 2026",
      "timestamp": "2026-03-26T00:03:18Z",
      "url": "https://decrypt.co/362391/australia-tokenized-asset-markets-rba-project",
      "image": "https://cdn.decrypt.co/wp-content/uploads/2026/03/Reserve-Bank-of-Australia-gID_7.jpg"
    },
    {
      "id": "icymi-20260326-84715c",
      "type": "icymi",
      "category": "crypto",
      "badge": "Bitcoin",
      "headline": "$15 Billion in Bitcoin Options Expire Friday as Trump's Iran Deadline Looms",
      "excerpt": "Bitcoin options worth $15 billion expire Friday\u2014just as a Trump-Iran diplomatic deadline runs out. Should traders expect greater volatility?",
      "source": "Decrypt",
      "date": "25 Mar 2026",
      "timestamp": "2026-03-25T20:19:02Z",
      "url": "https://decrypt.co/362352/15-billion-bitcoin-options-expire-friday-trump-iran-deadline",
      "image": "https://cdn.decrypt.co/wp-content/uploads/2025/09/Bitcoin-decrypt-style-24-gID_7.png"
    },
    {
      "id": "icymi-20260326-d7e222",
      "type": "icymi",
      "category": "crypto",
      "badge": "Stablecoin",
      "headline": "Circle Selloff 'Looks Overdone' Analysts Say as Shares Rise After Cathie\u2026",
      "excerpt": "Analysts argued that Circle's selloff was overblown after shares fell Tuesday amid crypto bill developments and a stablecoin rival's moves.",
      "source": "Decrypt",
      "date": "25 Mar 2026",
      "timestamp": "2026-03-25T19:03:49Z",
      "url": "https://decrypt.co/362336/circle-selloff-looks-overdone-shares-rise-cathie-wood-buys-dip",
      "image": "https://cdn.decrypt.co/wp-content/uploads/2025/06/usdc-circle-decrypt-gID_7.png"
    },
    {
      "id": "icymi-20260326-0bc487",
      "type": "icymi",
      "category": "crypto",
      "badge": "Bitcoin",
      "headline": "CoinShares Files for Bitcoin Volatility ETF Suite, Targeting BTC Price\u2026",
      "excerpt": "CoinShares filed for three Bitcoin volatility ETFs: a base, leveraged, and inverse fund. The funds could begin trading in early June 2026.",
      "source": "Decrypt",
      "date": "25 Mar 2026",
      "timestamp": "2026-03-25T18:16:32Z",
      "url": "https://decrypt.co/362330/coinshares-bitcoin-volatility-etf-suite-targeting-btc-price-swings",
      "image": "https://cdn.decrypt.co/wp-content/uploads/2025/07/Bitcoin-decrypt-style-25-gID_7.png"
    },
    {
      "id": "icymi-20260326-b97178",
      "type": "icymi",
      "category": "finance",
      "badge": "Finance",
      "headline": "Gulf states say they're ready for 'self defense' as stance shifts on Iran\u2026",
      "excerpt": "Gulf states have issued a joint statement on Thursday condemning Iran's \"blatant\" and \"criminal\" attacks against them.",
      "source": "CNBC",
      "date": "26 Mar 2026",
      "timestamp": "2026-03-26T09:49:14Z",
      "url": "https://www.cnbc.com/2026/03/26/gulf-states-ready-for-self-defense-against-iran-as-war-stance-shifts.html",
      "image": ""
    },
    {
      "id": "icymi-20260326-7cd87d",
      "type": "icymi",
      "category": "finance",
      "badge": "Finance",
      "headline": "Iran plans to charge ships for safe passage through Strait of Hormuz\u2026",
      "excerpt": "Officials in Tehran have drafted legislation to create a toll system where ships pay for safe passage through the waterway, Iranian media reported.",
      "source": "CNBC",
      "date": "26 Mar 2026",
      "timestamp": "2026-03-26T09:49:59Z",
      "url": "https://www.cnbc.com/2026/03/26/iran-plans-tolls-on-ships-passing-through-strait-of-hormuz.html",
      "image": ""
    },
    {
      "id": "icymi-20260326-ba1304",
      "type": "icymi",
      "category": "finance",
      "badge": "Finance",
      "headline": "Trump says Justices Barrett, Gorsuch \u2018sicken me\u2019 after Supreme Court\u2026",
      "excerpt": "The Supreme Court, in a 6-3 ruling, said President Trump did not have authority under the International Emergency Economic Powers Act to impose tariffs.",
      "source": "CNBC",
      "date": "26 Mar 2026",
      "timestamp": "2026-03-26T02:25:15Z",
      "url": "https://www.cnbc.com/2026/03/26/trump-supreme-court-tariffs-barrett-gorsuch-trade-ieepa-ruling.html",
      "image": ""
    },
    {
      "id": "icymi-20260326-0c0e5d",
      "type": "icymi",
      "category": "finance",
      "badge": "Markets",
      "headline": "Stock futures fall as traders monitor U.S.-Iran war developments: Live\u2026",
      "excerpt": "On Wednesday, the major averages rose on traders' hopes that there would soon be a resolution to the conflict in the Middle East.",
      "source": "CNBC",
      "date": "26 Mar 2026",
      "timestamp": "2026-03-26T10:11:08Z",
      "url": "https://www.cnbc.com/2026/03/25/stock-market-today-live-updates.html",
      "image": ""
    },
    {
      "id": "icymi-20260326-cd2a3f",
      "type": "icymi",
      "category": "finance",
      "badge": "Oil",
      "headline": "The oil market is in 'backwardation' \u2014 Here\u2019s what that means for energy\u2026",
      "excerpt": "Oil prices have been rocked by volatility since the U.S.-Iran war began.",
      "source": "CNBC",
      "date": "26 Mar 2026",
      "timestamp": "2026-03-26T08:22:15Z",
      "url": "https://www.cnbc.com/2026/03/26/market-trends-oil-futures-backwardation.html",
      "image": ""
    },
    {
      "id": "icymi-20260326-fc5e23",
      "type": "icymi",
      "category": "finance",
      "badge": "Markets",
      "headline": "Tesla stock true believers could be losing faith",
      "excerpt": "Scott Nations deciphers what the options market is telling us now about the cult stock.",
      "source": "CNBC",
      "date": "25 Mar 2026",
      "timestamp": "2026-03-25T19:50:32Z",
      "url": "https://www.cnbc.com/2026/03/25/tesla-stock-true-believers-could-be-losing-faith.html",
      "image": ""
    },
    {
      "id": "icymi-20260326-e04427",
      "type": "icymi",
      "category": "finance",
      "badge": "Finance",
      "headline": "White House posts cryptic videos, deletes one, fueling speculation online",
      "excerpt": "Two mysterious videos posted to the official White House X account on Wednesday night are generating buzz online, with the purpose of the short, vertically shot clips unclear.",
      "source": "CNBC",
      "date": "26 Mar 2026",
      "timestamp": "2026-03-26T05:18:26Z",
      "url": "https://www.cnbc.com/2026/03/26/trump-white-house-mysterious-videos-x-instagram.html",
      "image": ""
    },
    {
      "id": "icymi-20260326-d9d122",
      "type": "icymi",
      "category": "finance",
      "badge": "Finance",
      "headline": "Prediction market bets on sports, election, war would be verboten under\u2026",
      "excerpt": "Lawmakers have introduced a flurry of measures to rein-in prediction markets in recent weeks, as the platforms have come under increased scrutiny.",
      "source": "CNBC",
      "date": "26 Mar 2026",
      "timestamp": "2026-03-26T10:00:02Z",
      "url": "https://www.cnbc.com/2026/03/26/prediction-markets-sports-election-war-legislation-kalshi-polymarket.html",
      "image": ""
    },
    {
      "id": "icymi-20260326-ce20ca",
      "type": "icymi",
      "category": "finance",
      "badge": "Fed",
      "headline": "Reps Ro Khanna and Tim Burchett to push fraud probe across all 50 states",
      "excerpt": "Khanna, D-Calif., who is separately leading Democrats on a bill to impose a federal wealth tax, told CNBC in December he would introduce the fraud probe as soon as he found a Republican cosponsor.",
      "source": "CNBC",
      "date": "26 Mar 2026",
      "timestamp": "2026-03-26T10:00:02Z",
      "url": "https://www.cnbc.com/2026/03/26/reps-ro-khanna-and-tim-burchett-to-push-fraud-probe-across-all-50-states.html",
      "image": ""
    },
    {
      "id": "icymi-20260326-becd6c",
      "type": "icymi",
      "category": "finance",
      "badge": "Finance",
      "headline": "Meet Figure AI: The company behind the humanoid robot hosted by Melania\u2026",
      "excerpt": "The White House hosted its first humanoid robot guest, with first lady Melania Trump appearing alongside a robot from startup Figure AI.",
      "source": "CNBC",
      "date": "26 Mar 2026",
      "timestamp": "2026-03-26T09:09:51Z",
      "url": "https://www.cnbc.com/2026/03/26/figure-ai-the-robotics-company-hosted-by-melania-trump.html",
      "image": ""
    },
    {
      "id": "icymi-20260326-ca7a42",
      "type": "icymi",
      "category": "africa",
      "badge": "Africa",
      "headline": "News24 | Deep-fried calamari tentacles with plum, chilli, coriander and\u2026",
      "excerpt": "Golden. Crunchy. Irresistible. Best served hot and shared with cold drinks.",
      "source": "News24",
      "date": "26 Mar 2026",
      "timestamp": "2026-03-26T10:14:34Z",
      "url": "https://www.news24.com/life/food/recipes/deep-fried-calamari-tentacles-with-plum-chilli-coriander-and-mint-tartar-style-mayo-20260326-0550",
      "image": ""
    },
    {
      "id": "icymi-20260326-4fa369",
      "type": "icymi",
      "category": "africa",
      "badge": "Africa",
      "headline": "News24 | PODCAST | The Lead: The \u2018Cat\u2019 and a dozen cops in cuffs for\u2026",
      "excerpt": "Seasoned broadcast journalist Graeme Raubenheimer brings you The Lead, News24\u2019s definitive podcast for in-depth reporting.",
      "source": "News24",
      "date": "26 Mar 2026",
      "timestamp": "2026-03-26T10:14:34Z",
      "url": "https://www.news24.com/multimedia/podcasts/podcast-the-lead-the-cat-and-a-dozen-cops-in-cuffs-for-alleged-graft-20260325-1018",
      "image": ""
    },
    {
      "id": "icymi-20260326-cca64f",
      "type": "icymi",
      "category": "africa",
      "badge": "Africa",
      "headline": "News24 | Work from home back on the table in SA amid fuel price crisis",
      "excerpt": "Remote work is one of the few ways for households to limit the impact of a looming fuel-price shock.",
      "source": "News24",
      "date": "26 Mar 2026",
      "timestamp": "2026-03-26T10:14:34Z",
      "url": "https://www.news24.com/business/economy/work-from-home-back-on-the-table-in-sa-amid-fuel-price-crisis-20260325-0867",
      "image": ""
    },
    {
      "id": "icymi-20260326-cfcfb3",
      "type": "icymi",
      "category": "africa",
      "badge": "Africa",
      "headline": "News24 | Chaos in Parliament as debate on new lottery board chair explodes",
      "excerpt": "Debate on a shortlist of three candidates was suspended, then postponed, after MK and EFF MPs repeatedly raised points of order.",
      "source": "News24",
      "date": "26 Mar 2026",
      "timestamp": "2026-03-26T10:14:34Z",
      "url": "https://www.news24.com/business/economy/chaos-in-parliament-as-debate-on-new-lottery-board-chair-explodes-20260325-0881",
      "image": ""
    }
  ]
}